{
  "build_id": "validation-935c6960",
  "subsystem": "Validation",
  "intent": "Build a simple Python task management library (tasklib). It is not a production system. Its purpose is to validate that the Crafted Dev Agent build pipeline can close a complete dependency chain \u2014 from documentation through scaffold to working code \u2014 with real merges at each step.",
  "scope_statement": "Build a minimal Python task management library (tasklib) as defined in TRD-TASKLIB, consisting of five sequential dependency layers: documentation (README, ARCHITECTURE, API), package scaffold (src/tasklib/ with models/ and storage/ subpackages), task model (Task dataclass with TaskStatus enum per FR-1 through FR-7), in-memory task store (InMemoryTaskStore per FR-8 through FR-14), and CLI entry point (add/list/complete commands per FR-15 through FR-19), with a package root re-exporting the public API (FR-20). The purpose is to validate that the Crafted Dev Agent build pipeline can close a complete dependency chain \u2014 docs \u2192 scaffold \u2192 model \u2192 storage \u2192 CLI \u2014 with real merges at each step, per TRD-TASKLIB \u00a71.\n\nOperator on 'TRD-TASKLIB \u00a76 states no more than 3 implementation files pe':\nuse the PRD process to resolve any gaps. Use best practices.\n\nOperator on 'FR-1 specifies 'a unique identifier generated automatically ':\nuse the PRD process to resolve any gaps. Use best practices.\n\nOperator on 'The CLI (FR-15) must be 'runnable as a Python module' \u2014 shou':\nuse the PRD process to resolve any gaps. Use best practices.\n\nOperator on 'Should the test suite be delivered as a separate PR in the d':\nuse the PRD process to resolve any gaps. Use best practices.",
  "created_at": 1774808642.1068301,
  "updated_at": 1774810441.3304808,
  "updated_by": "todd-gould",
  "prd_plan": [
    {
      "prd_id": "PRD-001",
      "title": "Documentation Foundation \u2014 README, ARCHITECTURE, API",
      "status": "in_progress",
      "engineer_id": "",
      "pr_ids": [
        1,
        2,
        3,
        4,
        5,
        6,
        7,
        8
      ]
    },
    {
      "prd_id": "PRD-002",
      "title": "Package Scaffold \u2014 src/tasklib/ with models/ and storage/ subpackages",
      "status": "pending",
      "engineer_id": "",
      "pr_ids": []
    },
    {
      "prd_id": "PRD-003",
      "title": "Task Model \u2014 Task dataclass and TaskStatus enum (FR-1 through FR-7)",
      "status": "pending",
      "engineer_id": "",
      "pr_ids": []
    },
    {
      "prd_id": "PRD-004",
      "title": "In-Memory Task Store \u2014 InMemoryTaskStore (FR-8 through FR-14)",
      "status": "pending",
      "engineer_id": "",
      "pr_ids": []
    },
    {
      "prd_id": "PRD-005",
      "title": "CLI Entry Point \u2014 add, list, complete commands (FR-15 through FR-19)",
      "status": "pending",
      "engineer_id": "",
      "pr_ids": []
    },
    {
      "prd_id": "PRD-006",
      "title": "Package Root Public API Re-export (FR-20)",
      "status": "pending",
      "engineer_id": "",
      "pr_ids": []
    },
    {
      "prd_id": "PRD-007",
      "title": "End-to-End Integration Tests and API Documentation Amendment",
      "status": "pending",
      "engineer_id": "",
      "pr_ids": []
    }
  ],
  "pr_entries": {
    "1": {
      "prd_id": "PRD-001",
      "pr_num": 1,
      "title": "Add documentation foundation \u2014 README, ARCHITECTURE, API",
      "branch": "",
      "status": "done",
      "engineer_id": "",
      "pr_url": "https://github.com/todd-yousource-ai/Test/pull/45",
      "claimed_at": null,
      "started_at": null,
      "completed_at": 1774810441.330284,
      "depends_on_prs": [],
      "retry_count": 0,
      "failure_summary": "",
      "journal_path": "crafted-coordination/impl-journal/PR-001.md",
      "summary": "Creates the three seed documentation files that anchor the tasklib dependency chain per PRD-001. README.md describes the library purpose, package structure, and usage example. ARCHITECTURE.md describes the five-layer dependency chain (docs \u2192 scaffold \u2192 model \u2192 storage \u2192 CLI) with an ASCII diagram. API.md documents all planned public interfaces (Task fields, TaskStatus values, InMemoryTaskStore methods, CLI commands) with signatures, return types, and usage examples. No executable code is included. README.md and ARCHITECTURE.md become immutable after merge; API.md may be amended by a future update PR when interfaces are implemented.",
      "impl_files": [
        "README.md",
        "ARCHITECTURE.md",
        "API.md"
      ],
      "test_files": [],
      "language": "python",
      "framework": "pytest",
      "security_critical": false,
      "estimated_complexity": "low",
      "acceptance_criteria": [],
      "impl_plan": {}
    },
    "2": {
      "prd_id": "PRD-001",
      "pr_num": 2,
      "title": "Add tasklib package scaffold",
      "branch": "",
      "status": "available",
      "engineer_id": "",
      "pr_url": null,
      "claimed_at": null,
      "started_at": null,
      "completed_at": null,
      "depends_on_prs": [
        1
      ],
      "retry_count": 0,
      "failure_summary": "",
      "journal_path": "",
      "summary": "Create the minimal src/tasklib package skeleton with models and storage subpackages and empty __init__.py module entry points, establishing the import structure without any business logic.",
      "impl_files": [
        "src/tasklib/__init__.py",
        "src/tasklib/models/__init__.py",
        "src/tasklib/storage/__init__.py"
      ],
      "test_files": [],
      "language": "python",
      "framework": "pytest",
      "security_critical": false,
      "estimated_complexity": "low",
      "acceptance_criteria": [],
      "impl_plan": {}
    },
    "3": {
      "prd_id": "PRD-001",
      "pr_num": 3,
      "title": "Implement TaskStatus enum and Task dataclass",
      "branch": "",
      "status": "blocked",
      "engineer_id": "",
      "pr_url": null,
      "claimed_at": null,
      "started_at": null,
      "completed_at": null,
      "depends_on_prs": [
        2
      ],
      "retry_count": 0,
      "failure_summary": "",
      "journal_path": "",
      "summary": "Add the TaskStatus enum and Task dataclass implementing the documented task model requirements from API.md, including automatic uuid4 identifier generation, created_at timestamp, and core validation-friendly behavior. Re-exports Task and TaskStatus from the models subpackage __init__.py.",
      "impl_files": [
        "src/tasklib/models/task.py",
        "src/tasklib/models/__init__.py"
      ],
      "test_files": [
        "tests/tasklib/models/test_task.py"
      ],
      "language": "python",
      "framework": "pytest",
      "security_critical": false,
      "estimated_complexity": "medium",
      "acceptance_criteria": [],
      "impl_plan": {}
    },
    "4": {
      "prd_id": "PRD-001",
      "pr_num": 4,
      "title": "Re-export task model types from package root",
      "branch": "",
      "status": "blocked",
      "engineer_id": "",
      "pr_url": null,
      "claimed_at": null,
      "started_at": null,
      "completed_at": null,
      "depends_on_prs": [
        3
      ],
      "retry_count": 0,
      "failure_summary": "",
      "journal_path": "",
      "summary": "Expose Task and TaskStatus through the tasklib package public API so downstream layers can import from tasklib directly, in line with the planned interface contract documented in API.md.",
      "impl_files": [
        "src/tasklib/__init__.py"
      ],
      "test_files": [
        "tests/tasklib/test_public_api_models.py"
      ],
      "language": "python",
      "framework": "pytest",
      "security_critical": false,
      "estimated_complexity": "low",
      "acceptance_criteria": [],
      "impl_plan": {}
    },
    "5": {
      "prd_id": "PRD-001",
      "pr_num": 5,
      "title": "Implement InMemoryTaskStore",
      "branch": "",
      "status": "blocked",
      "engineer_id": "",
      "pr_url": null,
      "claimed_at": null,
      "started_at": null,
      "completed_at": null,
      "depends_on_prs": [
        3,
        4
      ],
      "retry_count": 0,
      "failure_summary": "",
      "journal_path": "",
      "summary": "Add InMemoryTaskStore with CRUD-style task management operations (add, get, list, complete, delete) required by the storage layer, using the Task model as its persisted in-memory entity. Re-exports InMemoryTaskStore from the storage subpackage __init__.py.",
      "impl_files": [
        "src/tasklib/storage/memory.py",
        "src/tasklib/storage/__init__.py"
      ],
      "test_files": [
        "tests/tasklib/storage/test_memory.py"
      ],
      "language": "python",
      "framework": "pytest",
      "security_critical": false,
      "estimated_complexity": "medium",
      "acceptance_criteria": [],
      "impl_plan": {}
    },
    "6": {
      "prd_id": "PRD-001",
      "pr_num": 6,
      "title": "Re-export InMemoryTaskStore from package root",
      "branch": "",
      "status": "blocked",
      "engineer_id": "",
      "pr_url": null,
      "claimed_at": null,
      "started_at": null,
      "completed_at": null,
      "depends_on_prs": [
        5
      ],
      "retry_count": 0,
      "failure_summary": "",
      "journal_path": "",
      "summary": "Expose InMemoryTaskStore through the tasklib package root public API to complete the library-facing import surface described in API.md.",
      "impl_files": [
        "src/tasklib/__init__.py"
      ],
      "test_files": [
        "tests/tasklib/test_public_api_storage.py"
      ],
      "language": "python",
      "framework": "pytest",
      "security_critical": false,
      "estimated_complexity": "low",
      "acceptance_criteria": [],
      "impl_plan": {}
    },
    "7": {
      "prd_id": "PRD-001",
      "pr_num": 7,
      "title": "Add tasklib CLI module",
      "branch": "",
      "status": "blocked",
      "engineer_id": "",
      "pr_url": null,
      "claimed_at": null,
      "started_at": null,
      "completed_at": null,
      "depends_on_prs": [
        5,
        6
      ],
      "retry_count": 0,
      "failure_summary": "",
      "journal_path": "",
      "summary": "Implement a module-runnable CLI entry point supporting add, list, and complete commands using argparse. Includes __main__.py delegating to cli.py so the interface is runnable via python -m tasklib.",
      "impl_files": [
        "src/tasklib/cli.py",
        "src/tasklib/__main__.py"
      ],
      "test_files": [
        "tests/tasklib/test_cli.py"
      ],
      "language": "python",
      "framework": "pytest",
      "security_critical": false,
      "estimated_complexity": "medium",
      "acceptance_criteria": [],
      "impl_plan": {}
    },
    "8": {
      "prd_id": "PRD-001",
      "pr_num": 8,
      "title": "Amend API.md to match implemented interfaces",
      "branch": "",
      "status": "blocked",
      "engineer_id": "",
      "pr_url": null,
      "claimed_at": null,
      "started_at": null,
      "completed_at": null,
      "depends_on_prs": [
        7
      ],
      "retry_count": 0,
      "failure_summary": "",
      "journal_path": "",
      "summary": "Update API.md after all implementation PRs have merged to confirm final public signatures, CLI invocation details, return types, and usage examples based on the actual merged code. This is an amendment to the existing file, not a re-creation.",
      "impl_files": [
        "API.md"
      ],
      "test_files": [],
      "language": "python",
      "framework": "pytest",
      "security_critical": false,
      "estimated_complexity": "low",
      "acceptance_criteria": [],
      "impl_plan": {}
    }
  },
  "knowledge_notes": [],
  "version": 3,
  "schema_version": 3,
  "agent_version": "39.143.0"
}